aluna/__init__.py
aluna/cli.py
aluna_cli-0.1.5.dist-info/METADATA
aluna_cli-0.1.5.dist-info/WHEEL
aluna_cli-0.1.5.dist-info/entry_points.txt
aluna_cli-0.1.5.dist-info/licenses/LICENSE
aluna_cli-0.1.5.dist-info/RECORD
