Metadata-Version: 2.4
Name: aluna-cli
Version: 0.1.5
Summary: CLI tool for downloading pathology slide files from Aluna
Project-URL: Homepage, https://alunalabs.ai
Project-URL: Repository, https://github.com/alunalabs/aluna-cli
Project-URL: Documentation, https://docs.alunalabs.ai
Author-email: Aluna Labs <support@alunalabs.ai>
License: MIT
License-File: LICENSE
Keywords: digital-pathology,medical-imaging,pathology,svs,whole-slide-imaging
Classifier: Development Status :: 3 - Alpha
Classifier: Intended Audience :: Healthcare Industry
Classifier: License :: OSI Approved :: MIT License
Classifier: Programming Language :: Python :: 3
Classifier: Programming Language :: Python :: 3.8
Classifier: Programming Language :: Python :: 3.9
Classifier: Programming Language :: Python :: 3.10
Classifier: Programming Language :: Python :: 3.11
Classifier: Programming Language :: Python :: 3.12
Classifier: Topic :: Scientific/Engineering :: Bio-Informatics
Classifier: Topic :: Scientific/Engineering :: Medical Science Apps.
Requires-Python: >=3.8
Requires-Dist: click>=8.0
Requires-Dist: httpx>=0.24.0
Requires-Dist: rich>=13.0
Requires-Dist: tqdm>=4.65.0
